<profile>

<RTLDesignHierarchy>
<TopModule>
<ModuleName>multi_core_multi_ram_ip</ModuleName>
</TopModule>
</RTLDesignHierarchy>

<ModuleInformation>
<Module>
<Name>multi_core_multi_ram_ip</Name>
<Loops>
<VITIS_LOOP_23_1></VITIS_LOOP_23_1>
</Loops>
<PerformanceEstimates>
<SummaryOfTimingAnalysis>
<TargetClockPeriod>10.00</TargetClockPeriod>
<ClockUncertainty>2.70</ClockUncertainty>
<EstimatedClockPeriod>7.300</EstimatedClockPeriod>
</SummaryOfTimingAnalysis>
<SummaryOfOverallLatency>
<Best-caseLatency>162</Best-caseLatency>
<Average-caseLatency>162</Average-caseLatency>
<Worst-caseLatency>162</Worst-caseLatency>
<Best-caseRealTimeLatency>1.620 us</Best-caseRealTimeLatency>
<Average-caseRealTimeLatency>1.620 us</Average-caseRealTimeLatency>
<Worst-caseRealTimeLatency>1.620 us</Worst-caseRealTimeLatency>
<PipelineInitiationInterval>160</PipelineInitiationInterval>
<PipelineType>loop auto-rewind (delay=0 clock cycles(s))</PipelineType>
</SummaryOfOverallLatency>
<SummaryOfLoopLatency>
<VITIS_LOOP_23_1>
<Name>VITIS_LOOP_23_1</Name>
<Slack>7.30</Slack>
<TripCount>16</TripCount>
<Latency>160</Latency>
<AbsoluteTimeLatency>1.600 us</AbsoluteTimeLatency>
<PipelineII>10</PipelineII>
<PipelineDepth>11</PipelineDepth>
<PipelineType>yes</PipelineType>
<InstanceList>
</InstanceList>
</VITIS_LOOP_23_1>
</SummaryOfLoopLatency>
<SummaryOfViolations>
<IssueType>-</IssueType>
<ViolationType>-</ViolationType>
<SourceLocation>../../multi_core_multi_ram_ip.cpp:3</SourceLocation>
<SummaryOfLoopViolations>
<VITIS_LOOP_23_1>
<Name>VITIS_LOOP_23_1</Name>
<IssueType>-</IssueType>
<ViolationType>-</ViolationType>
<SourceLocation>../../multi_core_multi_ram_ip.cpp:25</SourceLocation>
</VITIS_LOOP_23_1>
</SummaryOfLoopViolations>
</SummaryOfViolations>
</PerformanceEstimates>
<AreaEstimates>
<Resources>
<BRAM_18K>4</BRAM_18K>
<AVAIL_BRAM>280</AVAIL_BRAM>
<UTIL_BRAM>1</UTIL_BRAM>
<FF>1148</FF>
<AVAIL_FF>106400</AVAIL_FF>
<UTIL_FF>1</UTIL_FF>
<LUT>1285</LUT>
<AVAIL_LUT>53200</AVAIL_LUT>
<UTIL_LUT>2</UTIL_LUT>
<DSP>0</DSP>
<AVAIL_DSP>220</AVAIL_DSP>
<UTIL_DSP>0</UTIL_DSP>
<URAM>0</URAM>
<AVAIL_URAM>0</AVAIL_URAM>
<UTIL_URAM>0</UTIL_URAM>
</Resources>
</AreaEstimates>
<InterfaceSummary>
<RtlPorts>
<name>s_axi_control_AWVALID</name>
<Object>control</Object>
<Type>scalar</Type>
<IOProtocol>s_axi</IOProtocol>
<Dir>in</Dir>
<Bits>1</Bits>
<Attribute>unknown</Attribute>
<CType>int</CType>
<HasCtrl>1</HasCtrl>
</RtlPorts>
<RtlPorts>
<name>s_axi_control_AWREADY</name>
<Object>control</Object>
<Type>scalar</Type>
<IOProtocol>s_axi</IOProtocol>
<Dir>out</Dir>
<Bits>1</Bits>
<Attribute>unknown</Attribute>
<CType>int</CType>
<HasCtrl>1</HasCtrl>
</RtlPorts>
<RtlPorts>
<name>s_axi_control_AWADDR</name>
<Object>control</Object>
<Type>scalar</Type>
<IOProtocol>s_axi</IOProtocol>
<Dir>in</Dir>
<Bits>6</Bits>
<Attribute>unknown</Attribute>
<CType>int</CType>
<HasCtrl>1</HasCtrl>
</RtlPorts>
<RtlPorts>
<name>s_axi_control_WVALID</name>
<Object>control</Object>
<Type>scalar</Type>
<IOProtocol>s_axi</IOProtocol>
<Dir>in</Dir>
<Bits>1</Bits>
<Attribute>unknown</Attribute>
<CType>int</CType>
<HasCtrl>1</HasCtrl>
</RtlPorts>
<RtlPorts>
<name>s_axi_control_WREADY</name>
<Object>control</Object>
<Type>scalar</Type>
<IOProtocol>s_axi</IOProtocol>
<Dir>out</Dir>
<Bits>1</Bits>
<Attribute>unknown</Attribute>
<CType>int</CType>
<HasCtrl>1</HasCtrl>
</RtlPorts>
<RtlPorts>
<name>s_axi_control_WDATA</name>
<Object>control</Object>
<Type>scalar</Type>
<IOProtocol>s_axi</IOProtocol>
<Dir>in</Dir>
<Bits>32</Bits>
<Attribute>unknown</Attribute>
<CType>int</CType>
<HasCtrl>1</HasCtrl>
</RtlPorts>
<RtlPorts>
<name>s_axi_control_WSTRB</name>
<Object>control</Object>
<Type>scalar</Type>
<IOProtocol>s_axi</IOProtocol>
<Dir>in</Dir>
<Bits>4</Bits>
<Attribute>unknown</Attribute>
<CType>int</CType>
<HasCtrl>1</HasCtrl>
</RtlPorts>
<RtlPorts>
<name>s_axi_control_ARVALID</name>
<Object>control</Object>
<Type>scalar</Type>
<IOProtocol>s_axi</IOProtocol>
<Dir>in</Dir>
<Bits>1</Bits>
<Attribute>unknown</Attribute>
<CType>int</CType>
<HasCtrl>1</HasCtrl>
</RtlPorts>
<RtlPorts>
<name>s_axi_control_ARREADY</name>
<Object>control</Object>
<Type>scalar</Type>
<IOProtocol>s_axi</IOProtocol>
<Dir>out</Dir>
<Bits>1</Bits>
<Attribute>unknown</Attribute>
<CType>int</CType>
<HasCtrl>1</HasCtrl>
</RtlPorts>
<RtlPorts>
<name>s_axi_control_ARADDR</name>
<Object>control</Object>
<Type>scalar</Type>
<IOProtocol>s_axi</IOProtocol>
<Dir>in</Dir>
<Bits>6</Bits>
<Attribute>unknown</Attribute>
<CType>int</CType>
<HasCtrl>1</HasCtrl>
</RtlPorts>
<RtlPorts>
<name>s_axi_control_RVALID</name>
<Object>control</Object>
<Type>scalar</Type>
<IOProtocol>s_axi</IOProtocol>
<Dir>out</Dir>
<Bits>1</Bits>
<Attribute>unknown</Attribute>
<CType>int</CType>
<HasCtrl>1</HasCtrl>
</RtlPorts>
<RtlPorts>
<name>s_axi_control_RREADY</name>
<Object>control</Object>
<Type>scalar</Type>
<IOProtocol>s_axi</IOProtocol>
<Dir>in</Dir>
<Bits>1</Bits>
<Attribute>unknown</Attribute>
<CType>int</CType>
<HasCtrl>1</HasCtrl>
</RtlPorts>
<RtlPorts>
<name>s_axi_control_RDATA</name>
<Object>control</Object>
<Type>scalar</Type>
<IOProtocol>s_axi</IOProtocol>
<Dir>out</Dir>
<Bits>32</Bits>
<Attribute>unknown</Attribute>
<CType>int</CType>
<HasCtrl>1</HasCtrl>
</RtlPorts>
<RtlPorts>
<name>s_axi_control_RRESP</name>
<Object>control</Object>
<Type>scalar</Type>
<IOProtocol>s_axi</IOProtocol>
<Dir>out</Dir>
<Bits>2</Bits>
<Attribute>unknown</Attribute>
<CType>int</CType>
<HasCtrl>1</HasCtrl>
</RtlPorts>
<RtlPorts>
<name>s_axi_control_BVALID</name>
<Object>control</Object>
<Type>scalar</Type>
<IOProtocol>s_axi</IOProtocol>
<Dir>out</Dir>
<Bits>1</Bits>
<Attribute>unknown</Attribute>
<CType>int</CType>
<HasCtrl>1</HasCtrl>
</RtlPorts>
<RtlPorts>
<name>s_axi_control_BREADY</name>
<Object>control</Object>
<Type>scalar</Type>
<IOProtocol>s_axi</IOProtocol>
<Dir>in</Dir>
<Bits>1</Bits>
<Attribute>unknown</Attribute>
<CType>int</CType>
<HasCtrl>1</HasCtrl>
</RtlPorts>
<RtlPorts>
<name>s_axi_control_BRESP</name>
<Object>control</Object>
<Type>scalar</Type>
<IOProtocol>s_axi</IOProtocol>
<Dir>out</Dir>
<Bits>2</Bits>
<Attribute>unknown</Attribute>
<CType>int</CType>
<HasCtrl>1</HasCtrl>
</RtlPorts>
<RtlPorts>
<name>ap_clk</name>
<Object>multi_core_multi_ram_ip</Object>
<Type>return value</Type>
<Scope></Scope>
<IOProtocol>ap_ctrl_hs</IOProtocol>
<IOConfig></IOConfig>
<Dir>in</Dir>
<Bits>1</Bits>
<Attribute>control</Attribute>
</RtlPorts>
<RtlPorts>
<name>ap_rst_n</name>
<Object>multi_core_multi_ram_ip</Object>
<Type>return value</Type>
<Scope></Scope>
<IOProtocol>ap_ctrl_hs</IOProtocol>
<IOConfig></IOConfig>
<Dir>in</Dir>
<Bits>1</Bits>
<Attribute>control</Attribute>
</RtlPorts>
<RtlPorts>
<name>interrupt</name>
<Object>multi_core_multi_ram_ip</Object>
<Type>return value</Type>
<Scope></Scope>
<IOProtocol>ap_ctrl_hs</IOProtocol>
<IOConfig></IOConfig>
<Dir>out</Dir>
<Bits>1</Bits>
<Attribute>unknown</Attribute>
</RtlPorts>
<RtlPorts>
<name>m_axi_gmem_AWVALID</name>
<Object>gmem</Object>
<Type>pointer</Type>
<Scope></Scope>
<IOProtocol>m_axi</IOProtocol>
<IOConfig></IOConfig>
<Dir>out</Dir>
<Bits>1</Bits>
<Attribute>unknown</Attribute>
<CType>int</CType>
</RtlPorts>
<RtlPorts>
<name>m_axi_gmem_AWREADY</name>
<Object>gmem</Object>
<Type>pointer</Type>
<Scope></Scope>
<IOProtocol>m_axi</IOProtocol>
<IOConfig></IOConfig>
<Dir>in</Dir>
<Bits>1</Bits>
<Attribute>unknown</Attribute>
<CType>int</CType>
</RtlPorts>
<RtlPorts>
<name>m_axi_gmem_AWADDR</name>
<Object>gmem</Object>
<Type>pointer</Type>
<Scope></Scope>
<IOProtocol>m_axi</IOProtocol>
<IOConfig></IOConfig>
<Dir>out</Dir>
<Bits>64</Bits>
<Attribute>unknown</Attribute>
<CType>int</CType>
</RtlPorts>
<RtlPorts>
<name>m_axi_gmem_AWID</name>
<Object>gmem</Object>
<Type>pointer</Type>
<Scope></Scope>
<IOProtocol>m_axi</IOProtocol>
<IOConfig></IOConfig>
<Dir>out</Dir>
<Bits>1</Bits>
<Attribute>unknown</Attribute>
<CType>int</CType>
</RtlPorts>
<RtlPorts>
<name>m_axi_gmem_AWLEN</name>
<Object>gmem</Object>
<Type>pointer</Type>
<Scope></Scope>
<IOProtocol>m_axi</IOProtocol>
<IOConfig></IOConfig>
<Dir>out</Dir>
<Bits>8</Bits>
<Attribute>unknown</Attribute>
<CType>int</CType>
</RtlPorts>
<RtlPorts>
<name>m_axi_gmem_AWSIZE</name>
<Object>gmem</Object>
<Type>pointer</Type>
<Scope></Scope>
<IOProtocol>m_axi</IOProtocol>
<IOConfig></IOConfig>
<Dir>out</Dir>
<Bits>3</Bits>
<Attribute>unknown</Attribute>
<CType>int</CType>
</RtlPorts>
<RtlPorts>
<name>m_axi_gmem_AWBURST</name>
<Object>gmem</Object>
<Type>pointer</Type>
<Scope></Scope>
<IOProtocol>m_axi</IOProtocol>
<IOConfig></IOConfig>
<Dir>out</Dir>
<Bits>2</Bits>
<Attribute>unknown</Attribute>
<CType>int</CType>
</RtlPorts>
<RtlPorts>
<name>m_axi_gmem_AWLOCK</name>
<Object>gmem</Object>
<Type>pointer</Type>
<Scope></Scope>
<IOProtocol>m_axi</IOProtocol>
<IOConfig></IOConfig>
<Dir>out</Dir>
<Bits>2</Bits>
<Attribute>unknown</Attribute>
<CType>int</CType>
</RtlPorts>
<RtlPorts>
<name>m_axi_gmem_AWCACHE</name>
<Object>gmem</Object>
<Type>pointer</Type>
<Scope></Scope>
<IOProtocol>m_axi</IOProtocol>
<IOConfig></IOConfig>
<Dir>out</Dir>
<Bits>4</Bits>
<Attribute>unknown</Attribute>
<CType>int</CType>
</RtlPorts>
<RtlPorts>
<name>m_axi_gmem_AWPROT</name>
<Object>gmem</Object>
<Type>pointer</Type>
<Scope></Scope>
<IOProtocol>m_axi</IOProtocol>
<IOConfig></IOConfig>
<Dir>out</Dir>
<Bits>3</Bits>
<Attribute>unknown</Attribute>
<CType>int</CType>
</RtlPorts>
<RtlPorts>
<name>m_axi_gmem_AWQOS</name>
<Object>gmem</Object>
<Type>pointer</Type>
<Scope></Scope>
<IOProtocol>m_axi</IOProtocol>
<IOConfig></IOConfig>
<Dir>out</Dir>
<Bits>4</Bits>
<Attribute>unknown</Attribute>
<CType>int</CType>
</RtlPorts>
<RtlPorts>
<name>m_axi_gmem_AWREGION</name>
<Object>gmem</Object>
<Type>pointer</Type>
<Scope></Scope>
<IOProtocol>m_axi</IOProtocol>
<IOConfig></IOConfig>
<Dir>out</Dir>
<Bits>4</Bits>
<Attribute>unknown</Attribute>
<CType>int</CType>
</RtlPorts>
<RtlPorts>
<name>m_axi_gmem_AWUSER</name>
<Object>gmem</Object>
<Type>pointer</Type>
<Scope></Scope>
<IOProtocol>m_axi</IOProtocol>
<IOConfig></IOConfig>
<Dir>out</Dir>
<Bits>1</Bits>
<Attribute>unknown</Attribute>
<CType>int</CType>
</RtlPorts>
<RtlPorts>
<name>m_axi_gmem_WVALID</name>
<Object>gmem</Object>
<Type>pointer</Type>
<Scope></Scope>
<IOProtocol>m_axi</IOProtocol>
<IOConfig></IOConfig>
<Dir>out</Dir>
<Bits>1</Bits>
<Attribute>unknown</Attribute>
<CType>int</CType>
</RtlPorts>
<RtlPorts>
<name>m_axi_gmem_WREADY</name>
<Object>gmem</Object>
<Type>pointer</Type>
<Scope></Scope>
<IOProtocol>m_axi</IOProtocol>
<IOConfig></IOConfig>
<Dir>in</Dir>
<Bits>1</Bits>
<Attribute>unknown</Attribute>
<CType>int</CType>
</RtlPorts>
<RtlPorts>
<name>m_axi_gmem_WDATA</name>
<Object>gmem</Object>
<Type>pointer</Type>
<Scope></Scope>
<IOProtocol>m_axi</IOProtocol>
<IOConfig></IOConfig>
<Dir>out</Dir>
<Bits>32</Bits>
<Attribute>unknown</Attribute>
<CType>int</CType>
</RtlPorts>
<RtlPorts>
<name>m_axi_gmem_WSTRB</name>
<Object>gmem</Object>
<Type>pointer</Type>
<Scope></Scope>
<IOProtocol>m_axi</IOProtocol>
<IOConfig></IOConfig>
<Dir>out</Dir>
<Bits>4</Bits>
<Attribute>unknown</Attribute>
<CType>int</CType>
</RtlPorts>
<RtlPorts>
<name>m_axi_gmem_WLAST</name>
<Object>gmem</Object>
<Type>pointer</Type>
<Scope></Scope>
<IOProtocol>m_axi</IOProtocol>
<IOConfig></IOConfig>
<Dir>out</Dir>
<Bits>1</Bits>
<Attribute>unknown</Attribute>
<CType>int</CType>
</RtlPorts>
<RtlPorts>
<name>m_axi_gmem_WID</name>
<Object>gmem</Object>
<Type>pointer</Type>
<Scope></Scope>
<IOProtocol>m_axi</IOProtocol>
<IOConfig></IOConfig>
<Dir>out</Dir>
<Bits>1</Bits>
<Attribute>unknown</Attribute>
<CType>int</CType>
</RtlPorts>
<RtlPorts>
<name>m_axi_gmem_WUSER</name>
<Object>gmem</Object>
<Type>pointer</Type>
<Scope></Scope>
<IOProtocol>m_axi</IOProtocol>
<IOConfig></IOConfig>
<Dir>out</Dir>
<Bits>1</Bits>
<Attribute>unknown</Attribute>
<CType>int</CType>
</RtlPorts>
<RtlPorts>
<name>m_axi_gmem_ARVALID</name>
<Object>gmem</Object>
<Type>pointer</Type>
<Scope></Scope>
<IOProtocol>m_axi</IOProtocol>
<IOConfig></IOConfig>
<Dir>out</Dir>
<Bits>1</Bits>
<Attribute>unknown</Attribute>
<CType>int</CType>
</RtlPorts>
<RtlPorts>
<name>m_axi_gmem_ARREADY</name>
<Object>gmem</Object>
<Type>pointer</Type>
<Scope></Scope>
<IOProtocol>m_axi</IOProtocol>
<IOConfig></IOConfig>
<Dir>in</Dir>
<Bits>1</Bits>
<Attribute>unknown</Attribute>
<CType>int</CType>
</RtlPorts>
<RtlPorts>
<name>m_axi_gmem_ARADDR</name>
<Object>gmem</Object>
<Type>pointer</Type>
<Scope></Scope>
<IOProtocol>m_axi</IOProtocol>
<IOConfig></IOConfig>
<Dir>out</Dir>
<Bits>64</Bits>
<Attribute>unknown</Attribute>
<CType>int</CType>
</RtlPorts>
<RtlPorts>
<name>m_axi_gmem_ARID</name>
<Object>gmem</Object>
<Type>pointer</Type>
<Scope></Scope>
<IOProtocol>m_axi</IOProtocol>
<IOConfig></IOConfig>
<Dir>out</Dir>
<Bits>1</Bits>
<Attribute>unknown</Attribute>
<CType>int</CType>
</RtlPorts>
<RtlPorts>
<name>m_axi_gmem_ARLEN</name>
<Object>gmem</Object>
<Type>pointer</Type>
<Scope></Scope>
<IOProtocol>m_axi</IOProtocol>
<IOConfig></IOConfig>
<Dir>out</Dir>
<Bits>8</Bits>
<Attribute>unknown</Attribute>
<CType>int</CType>
</RtlPorts>
<RtlPorts>
<name>m_axi_gmem_ARSIZE</name>
<Object>gmem</Object>
<Type>pointer</Type>
<Scope></Scope>
<IOProtocol>m_axi</IOProtocol>
<IOConfig></IOConfig>
<Dir>out</Dir>
<Bits>3</Bits>
<Attribute>unknown</Attribute>
<CType>int</CType>
</RtlPorts>
<RtlPorts>
<name>m_axi_gmem_ARBURST</name>
<Object>gmem</Object>
<Type>pointer</Type>
<Scope></Scope>
<IOProtocol>m_axi</IOProtocol>
<IOConfig></IOConfig>
<Dir>out</Dir>
<Bits>2</Bits>
<Attribute>unknown</Attribute>
<CType>int</CType>
</RtlPorts>
<RtlPorts>
<name>m_axi_gmem_ARLOCK</name>
<Object>gmem</Object>
<Type>pointer</Type>
<Scope></Scope>
<IOProtocol>m_axi</IOProtocol>
<IOConfig></IOConfig>
<Dir>out</Dir>
<Bits>2</Bits>
<Attribute>unknown</Attribute>
<CType>int</CType>
</RtlPorts>
<RtlPorts>
<name>m_axi_gmem_ARCACHE</name>
<Object>gmem</Object>
<Type>pointer</Type>
<Scope></Scope>
<IOProtocol>m_axi</IOProtocol>
<IOConfig></IOConfig>
<Dir>out</Dir>
<Bits>4</Bits>
<Attribute>unknown</Attribute>
<CType>int</CType>
</RtlPorts>
<RtlPorts>
<name>m_axi_gmem_ARPROT</name>
<Object>gmem</Object>
<Type>pointer</Type>
<Scope></Scope>
<IOProtocol>m_axi</IOProtocol>
<IOConfig></IOConfig>
<Dir>out</Dir>
<Bits>3</Bits>
<Attribute>unknown</Attribute>
<CType>int</CType>
</RtlPorts>
<RtlPorts>
<name>m_axi_gmem_ARQOS</name>
<Object>gmem</Object>
<Type>pointer</Type>
<Scope></Scope>
<IOProtocol>m_axi</IOProtocol>
<IOConfig></IOConfig>
<Dir>out</Dir>
<Bits>4</Bits>
<Attribute>unknown</Attribute>
<CType>int</CType>
</RtlPorts>
<RtlPorts>
<name>m_axi_gmem_ARREGION</name>
<Object>gmem</Object>
<Type>pointer</Type>
<Scope></Scope>
<IOProtocol>m_axi</IOProtocol>
<IOConfig></IOConfig>
<Dir>out</Dir>
<Bits>4</Bits>
<Attribute>unknown</Attribute>
<CType>int</CType>
</RtlPorts>
<RtlPorts>
<name>m_axi_gmem_ARUSER</name>
<Object>gmem</Object>
<Type>pointer</Type>
<Scope></Scope>
<IOProtocol>m_axi</IOProtocol>
<IOConfig></IOConfig>
<Dir>out</Dir>
<Bits>1</Bits>
<Attribute>unknown</Attribute>
<CType>int</CType>
</RtlPorts>
<RtlPorts>
<name>m_axi_gmem_RVALID</name>
<Object>gmem</Object>
<Type>pointer</Type>
<Scope></Scope>
<IOProtocol>m_axi</IOProtocol>
<IOConfig></IOConfig>
<Dir>in</Dir>
<Bits>1</Bits>
<Attribute>unknown</Attribute>
<CType>int</CType>
</RtlPorts>
<RtlPorts>
<name>m_axi_gmem_RREADY</name>
<Object>gmem</Object>
<Type>pointer</Type>
<Scope></Scope>
<IOProtocol>m_axi</IOProtocol>
<IOConfig></IOConfig>
<Dir>out</Dir>
<Bits>1</Bits>
<Attribute>unknown</Attribute>
<CType>int</CType>
</RtlPorts>
<RtlPorts>
<name>m_axi_gmem_RDATA</name>
<Object>gmem</Object>
<Type>pointer</Type>
<Scope></Scope>
<IOProtocol>m_axi</IOProtocol>
<IOConfig></IOConfig>
<Dir>in</Dir>
<Bits>32</Bits>
<Attribute>unknown</Attribute>
<CType>int</CType>
</RtlPorts>
<RtlPorts>
<name>m_axi_gmem_RLAST</name>
<Object>gmem</Object>
<Type>pointer</Type>
<Scope></Scope>
<IOProtocol>m_axi</IOProtocol>
<IOConfig></IOConfig>
<Dir>in</Dir>
<Bits>1</Bits>
<Attribute>unknown</Attribute>
<CType>int</CType>
</RtlPorts>
<RtlPorts>
<name>m_axi_gmem_RID</name>
<Object>gmem</Object>
<Type>pointer</Type>
<Scope></Scope>
<IOProtocol>m_axi</IOProtocol>
<IOConfig></IOConfig>
<Dir>in</Dir>
<Bits>1</Bits>
<Attribute>unknown</Attribute>
<CType>int</CType>
</RtlPorts>
<RtlPorts>
<name>m_axi_gmem_RUSER</name>
<Object>gmem</Object>
<Type>pointer</Type>
<Scope></Scope>
<IOProtocol>m_axi</IOProtocol>
<IOConfig></IOConfig>
<Dir>in</Dir>
<Bits>1</Bits>
<Attribute>unknown</Attribute>
<CType>int</CType>
</RtlPorts>
<RtlPorts>
<name>m_axi_gmem_RRESP</name>
<Object>gmem</Object>
<Type>pointer</Type>
<Scope></Scope>
<IOProtocol>m_axi</IOProtocol>
<IOConfig></IOConfig>
<Dir>in</Dir>
<Bits>2</Bits>
<Attribute>unknown</Attribute>
<CType>int</CType>
</RtlPorts>
<RtlPorts>
<name>m_axi_gmem_BVALID</name>
<Object>gmem</Object>
<Type>pointer</Type>
<Scope></Scope>
<IOProtocol>m_axi</IOProtocol>
<IOConfig></IOConfig>
<Dir>in</Dir>
<Bits>1</Bits>
<Attribute>unknown</Attribute>
<CType>int</CType>
</RtlPorts>
<RtlPorts>
<name>m_axi_gmem_BREADY</name>
<Object>gmem</Object>
<Type>pointer</Type>
<Scope></Scope>
<IOProtocol>m_axi</IOProtocol>
<IOConfig></IOConfig>
<Dir>out</Dir>
<Bits>1</Bits>
<Attribute>unknown</Attribute>
<CType>int</CType>
</RtlPorts>
<RtlPorts>
<name>m_axi_gmem_BRESP</name>
<Object>gmem</Object>
<Type>pointer</Type>
<Scope></Scope>
<IOProtocol>m_axi</IOProtocol>
<IOConfig></IOConfig>
<Dir>in</Dir>
<Bits>2</Bits>
<Attribute>unknown</Attribute>
<CType>int</CType>
</RtlPorts>
<RtlPorts>
<name>m_axi_gmem_BID</name>
<Object>gmem</Object>
<Type>pointer</Type>
<Scope></Scope>
<IOProtocol>m_axi</IOProtocol>
<IOConfig></IOConfig>
<Dir>in</Dir>
<Bits>1</Bits>
<Attribute>unknown</Attribute>
<CType>int</CType>
</RtlPorts>
<RtlPorts>
<name>m_axi_gmem_BUSER</name>
<Object>gmem</Object>
<Type>pointer</Type>
<Scope></Scope>
<IOProtocol>m_axi</IOProtocol>
<IOConfig></IOConfig>
<Dir>in</Dir>
<Bits>1</Bits>
<Attribute>unknown</Attribute>
<CType>int</CType>
</RtlPorts>
<RtlPorts>
<name>local_ram_Addr_A</name>
<Object>local_ram</Object>
<Type>array</Type>
<Scope></Scope>
<IOProtocol>bram</IOProtocol>
<IOConfig></IOConfig>
<Dir>out</Dir>
<Bits>32</Bits>
<Attribute>address</Attribute>
<CType>int</CType>
</RtlPorts>
<RtlPorts>
<name>local_ram_EN_A</name>
<Object>local_ram</Object>
<Type>array</Type>
<Scope></Scope>
<IOProtocol>bram</IOProtocol>
<IOConfig></IOConfig>
<Dir>out</Dir>
<Bits>1</Bits>
<Attribute>control</Attribute>
<CType>int</CType>
</RtlPorts>
<RtlPorts>
<name>local_ram_WEN_A</name>
<Object>local_ram</Object>
<Type>array</Type>
<Scope></Scope>
<IOProtocol>bram</IOProtocol>
<IOConfig></IOConfig>
<Dir>out</Dir>
<Bits>4</Bits>
<Attribute>control</Attribute>
<CType>int</CType>
</RtlPorts>
<RtlPorts>
<name>local_ram_Din_A</name>
<Object>local_ram</Object>
<Type>array</Type>
<Scope></Scope>
<IOProtocol>bram</IOProtocol>
<IOConfig></IOConfig>
<Dir>out</Dir>
<Bits>32</Bits>
<Attribute>data</Attribute>
<CType>int</CType>
</RtlPorts>
<RtlPorts>
<name>local_ram_Dout_A</name>
<Object>local_ram</Object>
<Type>array</Type>
<Scope></Scope>
<IOProtocol>bram</IOProtocol>
<IOConfig></IOConfig>
<Dir>in</Dir>
<Bits>32</Bits>
<Attribute>data</Attribute>
<CType>int</CType>
</RtlPorts>
<RtlPorts>
<name>local_ram_Clk_A</name>
<Object>local_ram</Object>
<Type>array</Type>
<Scope></Scope>
<IOProtocol>bram</IOProtocol>
<IOConfig></IOConfig>
<Dir>out</Dir>
<Bits>1</Bits>
<Attribute>control</Attribute>
<CType>int</CType>
</RtlPorts>
<RtlPorts>
<name>local_ram_Rst_A</name>
<Object>local_ram</Object>
<Type>array</Type>
<Scope></Scope>
<IOProtocol>bram</IOProtocol>
<IOConfig></IOConfig>
<Dir>out</Dir>
<Bits>1</Bits>
<Attribute>control</Attribute>
<CType>int</CType>
</RtlPorts>
</InterfaceSummary>
</Module>
</ModuleInformation>

<FIFOInformation>
</FIFOInformation>

</profile>
